{
  "appgroup_id": "69c18520a5108b86af6bdb06",
  "appgroup_name": "EventOrganizer Pro",
  "apps": {
    "schnelleinladung": {
      "app_id": "69c184f6015010b253236847",
      "name": "Schnelleinladung",
      "controls": {
        "schnell_event": {
          "identifier": "schnell_event",
          "label": "Event",
          "type": "applookup",
          "subtype": "select",
          "fulltype": "applookup/select",
          "description": "A reference to a LivingApp record from the target lookup app 'Eventverwaltung' with the id `69c184f5bfd71417289848b6` (or `null`/`None`).\n\nThe field value will be a valid record URL in the form `https://my.living-apps.de/rest/apps/69c184f5bfd71417289848b6/<record-id>` (or `null`/`None`).\n\nDisplayed as single-select field in HTML pages.",
          "required": null,
          "in_list": true,
          "in_mobile_list": true,
          "in_text": true,
          "in_structured_search": false,
          "in_fulltext_search": false,
          "in_expert_search": true,
          "lookup_app": "https://my.living-apps.de/rest/apps/69c184f5bfd71417289848b6"
        },
        "schnell_gaeste": {
          "identifier": "schnell_gaeste",
          "label": "G\u00e4ste",
          "type": "multipleapplookup",
          "subtype": "select",
          "fulltype": "multipleapplookup/select",
          "description": "Arbitrary number of referenced LivingApp records from the target lookup app 'G\u00e4steverwaltung' with the id `69c184ea0b376d3c797865b1`.\n\nThe field value will be a list of valid record URLs in the form `https://my.living-apps.de/rest/apps/69c184ea0b376d3c797865b1/<record-id>`.\n\nDisplayed as a multi-select field in HTML pages.",
          "required": null,
          "in_list": true,
          "in_mobile_list": true,
          "in_text": true,
          "in_structured_search": false,
          "in_fulltext_search": false,
          "in_expert_search": true,
          "lookup_app": "https://my.living-apps.de/rest/apps/69c184ea0b376d3c797865b1"
        },
        "schnell_einladungsdatum": {
          "identifier": "schnell_einladungsdatum",
          "label": "Einladungsdatum",
          "type": "date",
          "subtype": "date",
          "fulltype": "date/date",
          "description": "A calendar date consisting of year, month and day (or `null`/`None`)\n\nThe field value will be a string in the format `<YYYY>-<MM>-<DD>` (or `null`/`None`).\n\nFor example: `2000-02-29`.",
          "required": null,
          "in_list": true,
          "in_mobile_list": false,
          "in_text": false,
          "in_structured_search": false,
          "in_fulltext_search": false,
          "in_expert_search": true
        },
        "schnell_notizen": {
          "identifier": "schnell_notizen",
          "label": "Notizen zur Einladung",
          "type": "string",
          "subtype": "textarea",
          "fulltype": "string/textarea",
          "description": "A string value that can contain multiple lines of text (or `null`/`None`).",
          "required": null,
          "in_list": true,
          "in_mobile_list": false,
          "in_text": false,
          "in_structured_search": false,
          "in_fulltext_search": false,
          "in_expert_search": true
        }
      }
    },
    "dienstleisterbuchung": {
      "app_id": "69c184f6df4d84221a69b827",
      "name": "Dienstleisterbuchung",
      "controls": {
        "buchung_event": {
          "identifier": "buchung_event",
          "label": "Event",
          "type": "applookup",
          "subtype": "select",
          "fulltype": "applookup/select",
          "description": "A reference to a LivingApp record from the target lookup app 'Eventverwaltung' with the id `69c184f5bfd71417289848b6` (or `null`/`None`).\n\nThe field value will be a valid record URL in the form `https://my.living-apps.de/rest/apps/69c184f5bfd71417289848b6/<record-id>` (or `null`/`None`).\n\nDisplayed as single-select field in HTML pages.",
          "required": null,
          "in_list": true,
          "in_mobile_list": true,
          "in_text": true,
          "in_structured_search": false,
          "in_fulltext_search": false,
          "in_expert_search": true,
          "lookup_app": "https://my.living-apps.de/rest/apps/69c184f5bfd71417289848b6"
        },
        "buchung_dienstleister": {
          "identifier": "buchung_dienstleister",
          "label": "Dienstleister",
          "type": "applookup",
          "subtype": "select",
          "fulltype": "applookup/select",
          "description": "A reference to a LivingApp record from the target lookup app 'Dienstleisterverwaltung' with the id `69c184f5969c07591f98b0b7` (or `null`/`None`).\n\nThe field value will be a valid record URL in the form `https://my.living-apps.de/rest/apps/69c184f5969c07591f98b0b7/<record-id>` (or `null`/`None`).\n\nDisplayed as single-select field in HTML pages.",
          "required": null,
          "in_list": true,
          "in_mobile_list": true,
          "in_text": true,
          "in_structured_search": false,
          "in_fulltext_search": false,
          "in_expert_search": true,
          "lookup_app": "https://my.living-apps.de/rest/apps/69c184f5969c07591f98b0b7"
        },
        "gebuchte_leistung": {
          "identifier": "gebuchte_leistung",
          "label": "Gebuchte Leistung",
          "type": "string",
          "subtype": "textarea",
          "fulltype": "string/textarea",
          "description": "A string value that can contain multiple lines of text (or `null`/`None`).",
          "required": null,
          "in_list": true,
          "in_mobile_list": false,
          "in_text": false,
          "in_structured_search": false,
          "in_fulltext_search": false,
          "in_expert_search": true
        },
        "vereinbarter_preis": {
          "identifier": "vereinbarter_preis",
          "label": "Vereinbarter Preis (\u20ac)",
          "type": "number",
          "subtype": null,
          "fulltype": "number",
          "description": "A decimal number value (or `null`/`None`).",
          "required": null,
          "in_list": true,
          "in_mobile_list": false,
          "in_text": false,
          "in_structured_search": false,
          "in_fulltext_search": false,
          "in_expert_search": true,
          "precision": null
        },
        "buchungsstatus": {
          "identifier": "buchungsstatus",
          "label": "Buchungsstatus",
          "type": "lookup",
          "subtype": "select",
          "fulltype": "lookup/select",
          "description": "One selected option of multiple available options (or `null`/`None`).\n\nThe available options are defined in the `lookup_data` attribute of this control.\n\nThe field value will be the key in this `lookup_data` attribute (or `null`/`None`).\n\nDisplayed as single-select field in HTML pages.",
          "required": null,
          "in_list": true,
          "in_mobile_list": false,
          "in_text": false,
          "in_structured_search": false,
          "in_fulltext_search": false,
          "in_expert_search": true,
          "lookup_data": {
            "angefragt": "Angefragt",
            "bestaetigt": "Best\u00e4tigt",
            "abgesagt": "Abgesagt",
            "abgeschlossen": "Abgeschlossen"
          }
        },
        "buchung_notizen": {
          "identifier": "buchung_notizen",
          "label": "Notizen",
          "type": "string",
          "subtype": "textarea",
          "fulltype": "string/textarea",
          "description": "A string value that can contain multiple lines of text (or `null`/`None`).",
          "required": null,
          "in_list": false,
          "in_mobile_list": false,
          "in_text": false,
          "in_structured_search": false,
          "in_fulltext_search": false,
          "in_expert_search": true
        }
      }
    },
    "einladungsmanagement": {
      "app_id": "69c184f5c06e59dd3b6338f5",
      "name": "Einladungsmanagement",
      "controls": {
        "einladung_event": {
          "identifier": "einladung_event",
          "label": "Event",
          "type": "applookup",
          "subtype": "select",
          "fulltype": "applookup/select",
          "description": "A reference to a LivingApp record from the target lookup app 'Eventverwaltung' with the id `69c184f5bfd71417289848b6` (or `null`/`None`).\n\nThe field value will be a valid record URL in the form `https://my.living-apps.de/rest/apps/69c184f5bfd71417289848b6/<record-id>` (or `null`/`None`).\n\nDisplayed as single-select field in HTML pages.",
          "required": null,
          "in_list": true,
          "in_mobile_list": true,
          "in_text": true,
          "in_structured_search": false,
          "in_fulltext_search": false,
          "in_expert_search": true,
          "lookup_app": "https://my.living-apps.de/rest/apps/69c184f5bfd71417289848b6"
        },
        "einladung_gast": {
          "identifier": "einladung_gast",
          "label": "Gast",
          "type": "applookup",
          "subtype": "select",
          "fulltype": "applookup/select",
          "description": "A reference to a LivingApp record from the target lookup app 'G\u00e4steverwaltung' with the id `69c184ea0b376d3c797865b1` (or `null`/`None`).\n\nThe field value will be a valid record URL in the form `https://my.living-apps.de/rest/apps/69c184ea0b376d3c797865b1/<record-id>` (or `null`/`None`).\n\nDisplayed as single-select field in HTML pages.",
          "required": null,
          "in_list": true,
          "in_mobile_list": true,
          "in_text": true,
          "in_structured_search": false,
          "in_fulltext_search": false,
          "in_expert_search": true,
          "lookup_app": "https://my.living-apps.de/rest/apps/69c184ea0b376d3c797865b1"
        },
        "einladungsdatum": {
          "identifier": "einladungsdatum",
          "label": "Einladungsdatum",
          "type": "date",
          "subtype": "date",
          "fulltype": "date/date",
          "description": "A calendar date consisting of year, month and day (or `null`/`None`)\n\nThe field value will be a string in the format `<YYYY>-<MM>-<DD>` (or `null`/`None`).\n\nFor example: `2000-02-29`.",
          "required": null,
          "in_list": true,
          "in_mobile_list": false,
          "in_text": false,
          "in_structured_search": false,
          "in_fulltext_search": false,
          "in_expert_search": true
        },
        "einladungsstatus": {
          "identifier": "einladungsstatus",
          "label": "Status",
          "type": "lookup",
          "subtype": "select",
          "fulltype": "lookup/select",
          "description": "One selected option of multiple available options (or `null`/`None`).\n\nThe available options are defined in the `lookup_data` attribute of this control.\n\nThe field value will be the key in this `lookup_data` attribute (or `null`/`None`).\n\nDisplayed as single-select field in HTML pages.",
          "required": null,
          "in_list": true,
          "in_mobile_list": false,
          "in_text": false,
          "in_structured_search": false,
          "in_fulltext_search": false,
          "in_expert_search": true,
          "lookup_data": {
            "eingeladen": "Eingeladen",
            "zugesagt": "Zugesagt",
            "abgesagt": "Abgesagt",
            "keine_antwort": "Keine Antwort"
          }
        },
        "einladung_notizen": {
          "identifier": "einladung_notizen",
          "label": "Notizen",
          "type": "string",
          "subtype": "textarea",
          "fulltype": "string/textarea",
          "description": "A string value that can contain multiple lines of text (or `null`/`None`).",
          "required": null,
          "in_list": true,
          "in_mobile_list": false,
          "in_text": false,
          "in_structured_search": false,
          "in_fulltext_search": false,
          "in_expert_search": true
        }
      }
    },
    "eventverwaltung": {
      "app_id": "69c184f5bfd71417289848b6",
      "name": "Eventverwaltung",
      "controls": {
        "event_name": {
          "identifier": "event_name",
          "label": "Eventname",
          "type": "string",
          "subtype": "text",
          "fulltype": "string/text",
          "description": "A string value not longer than 4000 characters (or `null`/`None`).",
          "required": null,
          "in_list": true,
          "in_mobile_list": true,
          "in_text": true,
          "in_structured_search": false,
          "in_fulltext_search": false,
          "in_expert_search": true
        },
        "event_datum": {
          "identifier": "event_datum",
          "label": "Datum und Uhrzeit",
          "type": "date",
          "subtype": "datetimeminute",
          "fulltype": "date/datetimeminute",
          "description": "A specific moment in time consisting of year, month, day, hour and minute (or `null`/`None`)\n\nThe field value will be a string in the format `<YYYY>-<MM>-<DD>T<HH>:<MM>` (or `null`/`None`).\n\nFor example: `2000-02-29T11:30`.",
          "required": null,
          "in_list": true,
          "in_mobile_list": true,
          "in_text": true,
          "in_structured_search": false,
          "in_fulltext_search": false,
          "in_expert_search": true
        },
        "event_strasse": {
          "identifier": "event_strasse",
          "label": "Stra\u00dfe",
          "type": "string",
          "subtype": "text",
          "fulltype": "string/text",
          "description": "A string value not longer than 4000 characters (or `null`/`None`).",
          "required": null,
          "in_list": true,
          "in_mobile_list": false,
          "in_text": false,
          "in_structured_search": false,
          "in_fulltext_search": false,
          "in_expert_search": true
        },
        "event_hausnummer": {
          "identifier": "event_hausnummer",
          "label": "Hausnummer",
          "type": "string",
          "subtype": "text",
          "fulltype": "string/text",
          "description": "A string value not longer than 4000 characters (or `null`/`None`).",
          "required": null,
          "in_list": true,
          "in_mobile_list": false,
          "in_text": false,
          "in_structured_search": false,
          "in_fulltext_search": false,
          "in_expert_search": true
        },
        "event_plz": {
          "identifier": "event_plz",
          "label": "Postleitzahl",
          "type": "string",
          "subtype": "text",
          "fulltype": "string/text",
          "description": "A string value not longer than 4000 characters (or `null`/`None`).",
          "required": null,
          "in_list": true,
          "in_mobile_list": false,
          "in_text": false,
          "in_structured_search": false,
          "in_fulltext_search": false,
          "in_expert_search": true
        },
        "event_ort": {
          "identifier": "event_ort",
          "label": "Stadt",
          "type": "string",
          "subtype": "text",
          "fulltype": "string/text",
          "description": "A string value not longer than 4000 characters (or `null`/`None`).",
          "required": null,
          "in_list": false,
          "in_mobile_list": false,
          "in_text": false,
          "in_structured_search": false,
          "in_fulltext_search": false,
          "in_expert_search": true
        },
        "event_beschreibung": {
          "identifier": "event_beschreibung",
          "label": "Beschreibung",
          "type": "string",
          "subtype": "textarea",
          "fulltype": "string/textarea",
          "description": "A string value that can contain multiple lines of text (or `null`/`None`).",
          "required": null,
          "in_list": false,
          "in_mobile_list": false,
          "in_text": false,
          "in_structured_search": false,
          "in_fulltext_search": false,
          "in_expert_search": true
        },
        "geplantes_budget": {
          "identifier": "geplantes_budget",
          "label": "Geplantes Budget (\u20ac)",
          "type": "number",
          "subtype": null,
          "fulltype": "number",
          "description": "A decimal number value (or `null`/`None`).",
          "required": null,
          "in_list": false,
          "in_mobile_list": false,
          "in_text": false,
          "in_structured_search": false,
          "in_fulltext_search": false,
          "in_expert_search": true,
          "precision": null
        },
        "event_status": {
          "identifier": "event_status",
          "label": "Eventstatus",
          "type": "lookup",
          "subtype": "select",
          "fulltype": "lookup/select",
          "description": "One selected option of multiple available options (or `null`/`None`).\n\nThe available options are defined in the `lookup_data` attribute of this control.\n\nThe field value will be the key in this `lookup_data` attribute (or `null`/`None`).\n\nDisplayed as single-select field in HTML pages.",
          "required": null,
          "in_list": false,
          "in_mobile_list": false,
          "in_text": false,
          "in_structured_search": false,
          "in_fulltext_search": false,
          "in_expert_search": true,
          "lookup_data": {
            "in_planung": "In Planung",
            "bestaetigt": "Best\u00e4tigt",
            "abgeschlossen": "Abgeschlossen",
            "abgesagt": "Abgesagt"
          }
        },
        "event_notizen": {
          "identifier": "event_notizen",
          "label": "Notizen",
          "type": "string",
          "subtype": "textarea",
          "fulltype": "string/textarea",
          "description": "A string value that can contain multiple lines of text (or `null`/`None`).",
          "required": null,
          "in_list": false,
          "in_mobile_list": false,
          "in_text": false,
          "in_structured_search": false,
          "in_fulltext_search": false,
          "in_expert_search": true
        }
      }
    },
    "dienstleisterverwaltung": {
      "app_id": "69c184f5969c07591f98b0b7",
      "name": "Dienstleisterverwaltung",
      "controls": {
        "firmenname": {
          "identifier": "firmenname",
          "label": "Firmenname",
          "type": "string",
          "subtype": "text",
          "fulltype": "string/text",
          "description": "A string value not longer than 4000 characters (or `null`/`None`).",
          "required": null,
          "in_list": true,
          "in_mobile_list": true,
          "in_text": true,
          "in_structured_search": false,
          "in_fulltext_search": false,
          "in_expert_search": true
        },
        "ansprechpartner_vorname": {
          "identifier": "ansprechpartner_vorname",
          "label": "Ansprechpartner Vorname",
          "type": "string",
          "subtype": "text",
          "fulltype": "string/text",
          "description": "A string value not longer than 4000 characters (or `null`/`None`).",
          "required": null,
          "in_list": true,
          "in_mobile_list": true,
          "in_text": true,
          "in_structured_search": false,
          "in_fulltext_search": false,
          "in_expert_search": true
        },
        "ansprechpartner_nachname": {
          "identifier": "ansprechpartner_nachname",
          "label": "Ansprechpartner Nachname",
          "type": "string",
          "subtype": "text",
          "fulltype": "string/text",
          "description": "A string value not longer than 4000 characters (or `null`/`None`).",
          "required": null,
          "in_list": true,
          "in_mobile_list": false,
          "in_text": false,
          "in_structured_search": false,
          "in_fulltext_search": false,
          "in_expert_search": true
        },
        "dl_email": {
          "identifier": "dl_email",
          "label": "E-Mail-Adresse",
          "type": "string",
          "subtype": "email",
          "fulltype": "string/email",
          "description": "A valid email address (or `null`/`None`).",
          "required": null,
          "in_list": true,
          "in_mobile_list": false,
          "in_text": false,
          "in_structured_search": false,
          "in_fulltext_search": false,
          "in_expert_search": true
        },
        "dl_telefon": {
          "identifier": "dl_telefon",
          "label": "Telefonnummer",
          "type": "string",
          "subtype": "tel",
          "fulltype": "string/tel",
          "description": "A valid telephone number (or `null`/`None`). Might include country prefix and should include area code.",
          "required": null,
          "in_list": true,
          "in_mobile_list": false,
          "in_text": false,
          "in_structured_search": false,
          "in_fulltext_search": false,
          "in_expert_search": true
        },
        "kategorie": {
          "identifier": "kategorie",
          "label": "Kategorie",
          "type": "lookup",
          "subtype": "select",
          "fulltype": "lookup/select",
          "description": "One selected option of multiple available options (or `null`/`None`).\n\nThe available options are defined in the `lookup_data` attribute of this control.\n\nThe field value will be the key in this `lookup_data` attribute (or `null`/`None`).\n\nDisplayed as single-select field in HTML pages.",
          "required": null,
          "in_list": false,
          "in_mobile_list": false,
          "in_text": false,
          "in_structured_search": false,
          "in_fulltext_search": false,
          "in_expert_search": true,
          "lookup_data": {
            "technik_av": "Technik / AV",
            "location": "Location",
            "musik_entertainment": "Musik / Entertainment",
            "fotografie_video": "Fotografie / Video",
            "dekoration": "Dekoration",
            "transport": "Transport",
            "sonstiges": "Sonstiges",
            "catering": "Catering"
          }
        },
        "dl_notizen": {
          "identifier": "dl_notizen",
          "label": "Notizen",
          "type": "string",
          "subtype": "textarea",
          "fulltype": "string/textarea",
          "description": "A string value that can contain multiple lines of text (or `null`/`None`).",
          "required": null,
          "in_list": false,
          "in_mobile_list": false,
          "in_text": false,
          "in_structured_search": false,
          "in_fulltext_search": false,
          "in_expert_search": true
        }
      }
    },
    "gaesteverwaltung": {
      "app_id": "69c184ea0b376d3c797865b1",
      "name": "G\u00e4steverwaltung",
      "controls": {
        "vorname": {
          "identifier": "vorname",
          "label": "Vorname",
          "type": "string",
          "subtype": "text",
          "fulltype": "string/text",
          "description": "A string value not longer than 4000 characters (or `null`/`None`).",
          "required": null,
          "in_list": true,
          "in_mobile_list": true,
          "in_text": true,
          "in_structured_search": false,
          "in_fulltext_search": false,
          "in_expert_search": true
        },
        "nachname": {
          "identifier": "nachname",
          "label": "Nachname",
          "type": "string",
          "subtype": "text",
          "fulltype": "string/text",
          "description": "A string value not longer than 4000 characters (or `null`/`None`).",
          "required": null,
          "in_list": true,
          "in_mobile_list": true,
          "in_text": true,
          "in_structured_search": false,
          "in_fulltext_search": false,
          "in_expert_search": true
        },
        "email": {
          "identifier": "email",
          "label": "E-Mail-Adresse",
          "type": "string",
          "subtype": "email",
          "fulltype": "string/email",
          "description": "A valid email address (or `null`/`None`).",
          "required": null,
          "in_list": true,
          "in_mobile_list": false,
          "in_text": false,
          "in_structured_search": false,
          "in_fulltext_search": false,
          "in_expert_search": true
        },
        "telefon": {
          "identifier": "telefon",
          "label": "Telefonnummer",
          "type": "string",
          "subtype": "tel",
          "fulltype": "string/tel",
          "description": "A valid telephone number (or `null`/`None`). Might include country prefix and should include area code.",
          "required": null,
          "in_list": true,
          "in_mobile_list": false,
          "in_text": false,
          "in_structured_search": false,
          "in_fulltext_search": false,
          "in_expert_search": true
        },
        "unternehmen": {
          "identifier": "unternehmen",
          "label": "Unternehmen",
          "type": "string",
          "subtype": "text",
          "fulltype": "string/text",
          "description": "A string value not longer than 4000 characters (or `null`/`None`).",
          "required": null,
          "in_list": true,
          "in_mobile_list": false,
          "in_text": false,
          "in_structured_search": false,
          "in_fulltext_search": false,
          "in_expert_search": true
        },
        "position": {
          "identifier": "position",
          "label": "Position / Funktion",
          "type": "string",
          "subtype": "text",
          "fulltype": "string/text",
          "description": "A string value not longer than 4000 characters (or `null`/`None`).",
          "required": null,
          "in_list": false,
          "in_mobile_list": false,
          "in_text": false,
          "in_structured_search": false,
          "in_fulltext_search": false,
          "in_expert_search": true
        },
        "notizen": {
          "identifier": "notizen",
          "label": "Notizen",
          "type": "string",
          "subtype": "textarea",
          "fulltype": "string/textarea",
          "description": "A string value that can contain multiple lines of text (or `null`/`None`).",
          "required": null,
          "in_list": false,
          "in_mobile_list": false,
          "in_text": false,
          "in_structured_search": false,
          "in_fulltext_search": false,
          "in_expert_search": true
        }
      }
    }
  },
  "metadata": {
    "apps_list": [
      "Schnelleinladung",
      "Dienstleisterbuchung",
      "Einladungsmanagement",
      "Eventverwaltung",
      "Dienstleisterverwaltung",
      "G\u00e4steverwaltung"
    ]
  }
}